oop_es_pg/__init__.py
oop_es_pg/database_conector.py
oop_es_pg/postgres_event_store.py
oop_es_pg/asyncpg/__init__.py
oop_es_pg/asyncpg/asyncpg_connector.py
oop_es_pg-0.3.0.dist-info/METADATA
oop_es_pg-0.3.0.dist-info/WHEEL
oop_es_pg-0.3.0.dist-info/top_level.txt
oop_es_pg-0.3.0.dist-info/RECORD
